dbhydra/__init__.py
dbhydra/dbhydra_core.py
dbhydra/test_migrator.py
dbhydra/src/__init__.py
dbhydra/src/abstract_db.py
dbhydra/src/abstract_table.py
dbhydra/src/bigquery_db.py
dbhydra/src/migrator.py
dbhydra/src/mongo_db.py
dbhydra/src/mysql_db.py
dbhydra/src/postgres_db.py
dbhydra/src/sqlserver_db.py
dbhydra/src/tables.py
dbhydra/src/xlsx_db.py
dbhydra/src/errors/__init__.py
dbhydra/src/errors/exceptions.py
dbhydra/tests/__init__.py
dbhydra/tests/test_cases.py
dbhydra/tests/test_mongo.py
dbhydra/tests/test_mysql_ddl.py
dbhydra/tests/test_sql.py
dbhydra-2.3.4.dist-info/LICENSE
dbhydra-2.3.4.dist-info/METADATA
dbhydra-2.3.4.dist-info/WHEEL
dbhydra-2.3.4.dist-info/top_level.txt
dbhydra-2.3.4.dist-info/RECORD
