Metadata-Version: 2.1
Name: dbhydra
Version: 2.3.4
Summary: Data science friendly ORM combining Python
Home-page: https://github.com/DovaX/dbhydra
Author: DovaX
Author-email: dovax.ai@gmail.com
Classifier: Programming Language :: Python :: 3
Classifier: License :: OSI Approved :: MIT License
Classifier: Operating System :: OS Independent
Requires-Python: >=3.6
License-File: LICENSE
Requires-Dist: pyodbc
Requires-Dist: pandas
Requires-Dist: pymysql
Requires-Dist: pymongo
Requires-Dist: google-cloud-bigquery
Requires-Dist: pydantic
